{
    "525": [
        33095,
        34547,
        9863,
        39575,
        31374,
        6802,
        9253,
        30484,
        38524,
        25777,
        16498,
        35760,
        14289,
        18119,
        8675,
        2605,
        6974,
        21353,
        24,
        4063,
        16123,
        40028,
        32899,
        7768,
        21033,
        22663,
        35330,
        36037,
        44942,
        4896,
        10884,
        5671,
        10015,
        34572,
        35835,
        3228,
        6377,
        10216,
        16241,
        15489,
        15417,
        12875,
        33003,
        37491,
        9074,
        7079,
        20931,
        9969,
        918,
        40961,
        30383,
        22099,
        31884,
        9314,
        30651,
        6512,
        30307,
        34451,
        29687,
        38084,
        33041,
        4903,
        14563,
        16157,
        19647,
        24629,
        24455,
        24439,
        13349,
        10110,
        9712,
        37601,
        5030,
        2251,
        10456,
        40803,
        31500,
        11843,
        157,
        24031,
        34620,
        7054,
        33028,
        934,
        15377,
        10080
    ],
    "1679": [
        33095,
        25835,
        35503,
        29163,
        4722,
        30375,
        23433,
        33362,
        34494,
        19365,
        9941,
        37450,
        37430,
        40403,
        2150,
        30015,
        10278,
        966,
        43691,
        37786,
        561,
        12711,
        710,
        22865,
        40620,
        21439,
        21,
        40904,
        40935,
        43350,
        1198,
        1932,
        34223,
        350,
        39184,
        2828,
        32607,
        38101,
        45577,
        34901,
        506,
        34451,
        31405,
        38254,
        1974,
        831,
        43735,
        604,
        48316,
        33899,
        6008,
        31537,
        33840,
        10490,
        21105,
        34800,
        8426,
        37281,
        6164,
        12679,
        33475,
        37962,
        1486,
        245,
        40272,
        7645,
        1721,
        1070,
        33948,
        15061,
        1678,
        1046,
        38670,
        23721,
        19163,
        37597,
        655,
        41930,
        39581,
        1045,
        39990,
        275,
        16419,
        1535,
        427
    ],
    "15": [
        33095,
        12815,
        38212,
        23433,
        21067,
        31229,
        19841,
        38331,
        12531,
        10162,
        33726,
        131,
        5984,
        130,
        36252,
        24211,
        39527,
        44516,
        322,
        40254,
        326,
        4477,
        3182,
        38089,
        2075,
        23213,
        5690,
        37379,
        45783,
        31452,
        14397,
        39905,
        1698,
        13585,
        33850,
        10800,
        32011,
        5525,
        36864,
        15085,
        37992,
        16035,
        1617,
        8129,
        13349,
        1142,
        16,
        16890,
        31456,
        242,
        13115,
        3298,
        38302,
        149,
        6895,
        9065
    ],
    "1989": [
        33095,
        534,
        5233,
        154,
        4028,
        1231,
        573,
        31592,
        527,
        2813,
        998,
        375,
        1184,
        189
    ],
    "2387": [
        32175,
        31914,
        33433,
        32282,
        32038,
        32039,
        32571,
        32105,
        38923,
        33775,
        31540,
        31680,
        32093,
        31633,
        32555,
        33668,
        31229,
        30911,
        33031,
        32309,
        32542,
        29758,
        32956,
        33803,
        34009,
        32595,
        31370,
        32681,
        31564,
        30806,
        30015,
        32673,
        31430,
        32881,
        33255,
        33023,
        31240,
        33037,
        33113,
        32899,
        32995,
        33377,
        33398,
        33341,
        31559,
        30749,
        33094,
        31098,
        31716,
        32013,
        32094,
        31994,
        32582,
        33274,
        32729,
        31178,
        33021,
        33414,
        34502,
        33540,
        33589,
        33835,
        32961,
        32697,
        38611,
        31439,
        32360,
        34156,
        32353,
        31498,
        32962,
        32572,
        32585,
        32876,
        33419,
        31848,
        32603,
        34034,
        32998,
        32454,
        31223,
        36530,
        38612,
        32983,
        32670,
        33473,
        31621,
        31646,
        32682,
        33811,
        31953,
        34235,
        35542,
        36611,
        33099,
        32228,
        33002,
        32785,
        34013,
        40672,
        33051,
        32828,
        33003,
        31722,
        31452,
        34233,
        34754,
        31764,
        32606,
        31904,
        31793,
        32999,
        32379,
        33933,
        31631,
        35319,
        32607,
        32947,
        30016,
        31741,
        32944,
        32313,
        31414,
        31442,
        33795,
        28013,
        33541,
        31588,
        33771,
        31804,
        33262,
        32948,
        33394,
        31890,
        32772,
        31790,
        32979,
        31404,
        32483,
        31173,
        32792,
        33434,
        32171,
        31821,
        31884,
        32608,
        30895,
        33314,
        32491,
        31580,
        32526,
        30795,
        33299,
        38129,
        32182,
        30654,
        33814,
        31798,
        31157,
        31610,
        31771,
        33690,
        32438,
        38128,
        33462,
        32568,
        33253,
        32011,
        33197,
        31376,
        32829,
        32805,
        31080,
        33727,
        33479,
        28391,
        31405,
        34488,
        27833,
        34410,
        33392,
        33041,
        33245,
        31706,
        34234,
        32977,
        31859,
        34503,
        31630,
        32023,
        31049,
        36551,
        31737,
        33490,
        34677,
        33241,
        31815,
        32691,
        33746,
        32696,
        31043,
        32245,
        32648,
        32906,
        32301,
        31733,
        31988,
        32494,
        33244,
        33975,
        37927,
        32601,
        31636,
        31964,
        31670,
        32867,
        28623,
        32084,
        31933,
        31637,
        31339,
        31952,
        33985,
        32083,
        30652,
        32935,
        32370,
        31845,
        34309,
        30831,
        32664,
        32866,
        32686,
        33240,
        31478,
        32274,
        33421,
        32214,
        31338,
        32189,
        31753,
        31163,
        31500,
        33222,
        31417,
        33188,
        33026,
        33044,
        31710,
        32663,
        32802,
        34664,
        33046,
        34667,
        31109,
        33028,
        34292,
        42740,
        34077,
        33572,
        33946,
        32717,
        34207,
        34676,
        37219,
        33290,
        38074
    ],
    "2326": [
        33095,
        32175,
        34547,
        19775,
        24893,
        32282,
        36949,
        35788,
        9863,
        28171,
        39940,
        12815,
        170,
        35629,
        3369,
        38212,
        2161,
        31374,
        40902,
        4722,
        10378,
        38524,
        22101,
        7082,
        25777,
        5262,
        2923,
        16498,
        35760,
        7724,
        3588,
        21507,
        1517,
        5958,
        2562,
        1965,
        6098,
        8557,
        23273,
        32105,
        8726,
        34823,
        8407,
        37662,
        10109,
        39456,
        33775,
        23433,
        14289,
        2216,
        31680,
        11371,
        5226,
        21067,
        17211,
        17821,
        154,
        3470,
        1559,
        33417,
        30649,
        5485,
        2451,
        31229,
        5034,
        43969,
        47257,
        341,
        22687,
        11123,
        12531,
        13141,
        2104,
        32542,
        29758,
        22319,
        4581,
        1548,
        42774,
        1541,
        100,
        27899,
        7588,
        9926,
        25,
        12445,
        390,
        39194,
        2605,
        14227,
        582,
        1642,
        1568,
        3332,
        15125,
        18139,
        31370,
        19981,
        8687,
        1728,
        10162,
        12431,
        2158,
        5277,
        620,
        11499,
        36511,
        846,
        37521,
        4021,
        32673,
        114,
        21353,
        22,
        30437,
        2903,
        24,
        658,
        31430,
        6114,
        12321,
        28861,
        4063,
        407,
        18121,
        6444,
        32881,
        1608,
        16049,
        1712,
        42249,
        33255,
        36943,
        33726,
        5005,
        36513,
        3455,
        8542,
        6213,
        1108,
        22135,
        41402,
        966,
        16123,
        18179,
        40028,
        43691,
        34612,
        173,
        38004,
        32899,
        174,
        3974,
        400,
        2965,
        13663,
        20709,
        6582,
        38610,
        6,
        37779,
        40392,
        11763,
        39966,
        6203,
        25157,
        37799,
        10033,
        10073,
        131,
        8311,
        29854,
        6500,
        1065,
        28979,
        200,
        41389,
        419,
        1372,
        33398,
        38474,
        28677,
        42361,
        42938,
        37786,
        338,
        21487,
        24277,
        44942,
        45653,
        4663,
        529,
        687,
        40907,
        623,
        43325,
        38480,
        5300,
        18041,
        20473,
        34019,
        42250,
        1508,
        30240,
        3009,
        7058,
        5832,
        35067,
        3859,
        38853,
        39183,
        30740,
        42391,
        508,
        28297,
        45,
        329,
        3672,
        5984,
        861,
        3457,
        19315,
        2934,
        17777,
        5074,
        1000,
        39710,
        34798,
        31098,
        479,
        481,
        1713,
        26395,
        10495,
        34550,
        26443,
        42351,
        3768,
        130,
        10884,
        3091,
        482,
        3044,
        35298,
        2747,
        5671,
        710,
        392,
        65,
        34799,
        24405,
        26243,
        43439,
        35789,
        177,
        37722,
        10015,
        14075,
        3972,
        43608,
        34572,
        3000,
        28927,
        2486,
        969,
        210,
        2014,
        3125,
        40333,
        4752,
        38481,
        6056,
        12403,
        30279,
        1254,
        21639,
        24701,
        14355,
        3137,
        21325,
        1744,
        1167,
        39247,
        45560,
        41226,
        3806,
        36652,
        6586,
        343,
        4214,
        32729,
        156,
        2993,
        1293,
        46422,
        183,
        64,
        41812,
        40908,
        41349,
        916,
        33478,
        38203,
        5040,
        550,
        3827,
        40911,
        9441,
        31783,
        3228,
        34262,
        6377,
        21,
        37920,
        21085,
        41587,
        42822,
        4853,
        3819,
        28,
        10216,
        2608,
        11665,
        2011,
        553,
        1199,
        33540,
        12929,
        907,
        37890,
        238,
        7720,
        29,
        4618,
        5992,
        9884,
        34566,
        42205,
        27681,
        11837,
        16526,
        37975,
        34591,
        1562,
        42627,
        919,
        40682,
        37616,
        1218,
        39469,
        9883,
        40957,
        46569,
        178,
        18497,
        30567,
        23673,
        3024,
        9331,
        46352,
        1607,
        35843,
        21939,
        2404,
        34096,
        1985,
        16241,
        2718,
        39527,
        1538,
        4486,
        5530,
        2741,
        44516,
        795,
        40935,
        39948,
        322,
        10379,
        1127,
        41686,
        4548,
        2231,
        48491,
        40254,
        691,
        326,
        37522,
        47778,
        2931,
        2159,
        34745,
        42892,
        853,
        40526,
        311,
        9916,
        21435,
        4940,
        36838,
        33538,
        33419,
        5250,
        39592,
        16303,
        3433,
        3765,
        40852,
        30503,
        1040,
        37345,
        35180,
        457,
        32603,
        325,
        10607,
        1941,
        4477,
        5249,
        19,
        40906,
        4331,
        2933,
        32454,
        42625,
        44204,
        36726,
        3182,
        970,
        38089,
        42714,
        4062,
        10165,
        15489,
        943,
        2402,
        8476,
        3023,
        43629,
        1491,
        32983,
        8216,
        1060,
        197,
        28819,
        23623,
        1589,
        175,
        718,
        5200,
        47591,
        4081,
        6868,
        44940,
        10049,
        15417,
        40746,
        35370,
        10346,
        35964,
        1062,
        282,
        2075,
        3907,
        31646,
        48363,
        2112,
        39617,
        33811,
        1246,
        2686,
        23213,
        20507,
        48442,
        33337,
        162,
        2703,
        41380,
        386,
        40436,
        1128,
        337,
        3579,
        36565,
        17549,
        41025,
        2716,
        5690,
        23,
        1706,
        41488,
        32228,
        4038,
        40136,
        24135,
        36728,
        38098,
        6971,
        41332,
        45207,
        34350,
        31227,
        3021,
        5841,
        1842,
        42517,
        1492,
        1537,
        35834,
        20001,
        19831,
        2912,
        37379,
        2706,
        8123,
        28869,
        2705,
        1771,
        35672,
        27787,
        45783,
        42897,
        30410,
        3550,
        32828,
        627,
        34088,
        23351,
        10250,
        38797,
        37491,
        31722,
        6055,
        1214,
        4591,
        25517,
        3022,
        31440,
        3226,
        9074,
        3129,
        2921,
        42962,
        2518,
        25939,
        8765,
        1873,
        31904,
        2929,
        14397,
        3001,
        35062,
        15863,
        9426,
        2709,
        3673,
        37487,
        161,
        16518,
        1936,
        1547,
        35183,
        35821,
        340,
        5032,
        7655,
        1698,
        44881,
        591,
        32379,
        17705,
        34383,
        3281,
        40504,
        1493,
        14513,
        36793,
        42340,
        13585,
        12391,
        558,
        34055,
        10271,
        39539,
        7647,
        44961,
        15749,
        4936,
        2740,
        13535,
        38101,
        3655,
        37990,
        41619,
        37029,
        34106,
        18115,
        6397,
        7307,
        35075,
        31741,
        4151,
        880,
        10847,
        3020,
        67,
        1735,
        33371,
        57,
        490,
        714,
        31414,
        26351,
        962,
        1243,
        1705,
        10197,
        24833,
        2835,
        18771,
        35078,
        1300,
        5028,
        5278,
        7661,
        22831,
        13409,
        44511,
        34580,
        40854,
        12471,
        9969,
        35025,
        1583,
        34577,
        41491,
        2762,
        1738,
        877,
        3297,
        41762,
        4056,
        7761,
        9513,
        9996,
        18897,
        36800,
        11697,
        6629,
        31588,
        3002,
        17389,
        33506,
        8,
        19873,
        273,
        43763,
        31804,
        105,
        39792,
        40367,
        39799,
        28249,
        385,
        477,
        918,
        7592,
        1470,
        1189,
        23755,
        3131,
        24415,
        1546,
        3356,
        1371,
        41556,
        24909,
        31422,
        37956,
        9510,
        1057,
        40513,
        36266,
        37979,
        40358,
        27525,
        10800,
        5375,
        38753,
        3418,
        31173,
        2501,
        34052,
        18411,
        31821,
        5658,
        20,
        1708,
        40529,
        298,
        3136,
        886,
        42192,
        838,
        740,
        36231,
        3619,
        6324,
        16201,
        5688,
        2565,
        37560,
        1356,
        12763,
        2213,
        8763,
        9106,
        31580,
        1883,
        22535,
        31777,
        19363,
        23013,
        30205,
        68,
        30123,
        30795,
        1519,
        37447,
        44387,
        1453,
        12039,
        30654,
        6030,
        41266,
        750,
        10030,
        26441,
        37106,
        2004,
        28977,
        15,
        6604,
        470,
        2986,
        21405,
        21185,
        3947,
        53,
        1550,
        25013,
        40128,
        107,
        35557,
        40956,
        31610,
        38671,
        31771,
        18845,
        1083,
        12031,
        30651,
        6512,
        8194,
        37989,
        7674,
        17505,
        30307,
        2771,
        33462,
        45055,
        8764,
        12365,
        42963,
        6981,
        5908,
        22043,
        33253,
        19429,
        5968,
        21995,
        5941,
        532,
        2036,
        5258,
        331,
        16393,
        8538,
        36028,
        16918,
        9919,
        50,
        40483,
        34565,
        11457,
        280,
        951,
        37007,
        31376,
        506,
        269,
        39701,
        32805,
        7627,
        28423,
        31080,
        34451,
        4483,
        1704,
        27663,
        394,
        1196,
        9587,
        11633,
        889,
        4690,
        136,
        22199,
        14511,
        25429,
        6067,
        263,
        2723,
        41946,
        20431,
        2035,
        22817,
        45425,
        39463,
        495,
        633,
        3225,
        39808,
        1668,
        10554,
        2694,
        388,
        1690,
        4549,
        12467,
        42090,
        3391,
        5525,
        38276,
        967,
        1775,
        1667,
        2985,
        2227,
        5217,
        3077,
        37475,
        1485,
        1974,
        37259,
        33487,
        103,
        35972,
        31706,
        1327,
        3656,
        23945,
        9934,
        2204,
        3213,
        2772,
        852,
        4903,
        15915,
        34888,
        1239,
        5039,
        41694,
        11739,
        36548,
        2552,
        18893,
        9736,
        36864,
        38226,
        9479,
        32949,
        10870,
        1050,
        11061,
        971,
        19647,
        22145,
        1110,
        5023,
        5473,
        16317,
        589,
        38003,
        22507,
        5597,
        7793,
        40834,
        3193,
        345,
        40059,
        1483,
        34636,
        616,
        37403,
        7575,
        8410,
        287,
        6093,
        11771,
        33490,
        1660,
        1599,
        38408,
        6024,
        2786,
        132,
        1893,
        8415,
        34525,
        2076,
        9013,
        19855,
        551,
        5276,
        37338,
        284,
        37171,
        38397,
        5997,
        38993,
        39196,
        36124,
        344,
        29325,
        6712,
        41833,
        45572,
        20509,
        22893,
        1516,
        33206,
        1745,
        1661,
        261,
        33743,
        2834,
        530,
        36456,
        229,
        38889,
        16894,
        2907,
        18495,
        998,
        25649,
        38186,
        31043,
        37140,
        42414,
        7619,
        35860,
        32648,
        3359,
        9028,
        17,
        1473,
        729,
        25183,
        24439,
        9181,
        31733,
        34825,
        159,
        2704,
        3335,
        18465,
        40004,
        577,
        32494,
        5273,
        34542,
        33,
        2243,
        33975,
        12979,
        37806,
        35241,
        34934,
        33486,
        6702,
        38080,
        1722,
        1554,
        1664,
        1219,
        6116,
        38814,
        1592,
        288,
        16035,
        230,
        36976,
        32601,
        31636,
        1123,
        40748,
        9834,
        801,
        521,
        2253,
        30230,
        5618,
        10889,
        33203,
        3841,
        41466,
        10620,
        1617,
        1628,
        38000,
        16910,
        31964,
        2252,
        31670,
        40833,
        34984,
        857,
        32867,
        5967,
        624,
        15059,
        7177,
        2229,
        31933,
        1509,
        915,
        10460,
        10490,
        39195,
        37991,
        34712,
        31339,
        28071,
        38731,
        3710,
        38881,
        3006,
        2789,
        364,
        35983,
        8129,
        21105,
        1669,
        39199,
        2508,
        1180,
        31952,
        21863,
        8394,
        1087,
        32878,
        22433,
        39730,
        3653,
        29785,
        21681,
        8426,
        39017,
        13349,
        129,
        29589,
        3545,
        37281,
        21809,
        810,
        11703,
        42590,
        1740,
        914,
        30652,
        6509,
        20031,
        40397,
        3807,
        32935,
        13231,
        260,
        2034,
        36049,
        141,
        6707,
        30694,
        240,
        5162,
        40010,
        11241,
        36934,
        32370,
        10370,
        9533,
        1472,
        38656,
        6164,
        6117,
        1142,
        2963,
        34964,
        3272,
        2224,
        2542,
        18001,
        330,
        5834,
        996,
        5071,
        277,
        487,
        28891,
        20899,
        36296,
        7160,
        12679,
        16,
        5760,
        33475,
        384,
        37964,
        395,
        2503,
        4039,
        40591,
        246,
        24417,
        48252,
        20583,
        1325,
        32686,
        37105,
        26055,
        241,
        15045,
        27947,
        24765,
        5140,
        953,
        4999,
        34831,
        36094,
        9712,
        33240,
        31478,
        21431,
        28883,
        1486,
        841,
        245,
        16890,
        17741,
        14829,
        36873,
        3389,
        467,
        22777,
        38883,
        40839,
        14653,
        5089,
        7580,
        2165,
        32214,
        253,
        5030,
        5079,
        45613,
        3464,
        16982,
        39030,
        39337,
        637,
        3081,
        2602,
        9656,
        10987,
        135,
        1374,
        5678,
        9367,
        297,
        1604,
        7867,
        1316,
        2043,
        14527,
        13331,
        242,
        102,
        31163,
        4898,
        36649,
        35222,
        5052,
        2130,
        9613,
        39198,
        185,
        145,
        2037,
        1844,
        6045,
        236,
        13203,
        301,
        912,
        516,
        403,
        1222,
        1161,
        10177,
        6033,
        776,
        1567,
        122,
        14045,
        1721,
        5476,
        12413,
        335,
        20457,
        840,
        110,
        123,
        3568,
        48483,
        22247,
        74,
        37188,
        37999,
        39533,
        40417,
        1471,
        1465,
        2405,
        1337,
        14719,
        1806,
        738,
        11761,
        5114,
        667,
        1606,
        231,
        1674,
        8244,
        334,
        33354,
        18055,
        1678,
        40776,
        286,
        20075,
        3298,
        5962,
        10709,
        5973,
        1707,
        1046,
        33988,
        3345,
        5835,
        16355,
        1685,
        34933,
        21743,
        4725,
        292,
        18689,
        35376,
        38691,
        38302,
        25681,
        121,
        649,
        32136,
        10465,
        296,
        11769,
        519,
        15613,
        38680,
        157,
        16353,
        39783,
        34382,
        1848,
        690,
        3808,
        234,
        14345,
        6811,
        626,
        968,
        1614,
        15565,
        646,
        40716,
        37517,
        1572,
        4439,
        33731,
        4196,
        3053,
        7479,
        2556,
        2335,
        2116,
        2964,
        9493,
        913,
        799,
        1536,
        5274,
        2400,
        888,
        233,
        276,
        1021,
        24031,
        6645,
        15109,
        16706,
        1810,
        248,
        36525,
        10338,
        37597,
        9938,
        31109,
        36029,
        149,
        38476,
        37325,
        2800,
        1250,
        38778,
        104,
        2222,
        1573,
        31018,
        3231,
        501,
        576,
        4192,
        39570,
        39534,
        2471,
        3514,
        7054,
        4814,
        37086,
        106,
        257,
        1563,
        634,
        9455,
        9905,
        18,
        42568,
        435,
        10838,
        37117,
        3116,
        6571,
        1482,
        5150,
        3844,
        2012,
        1956,
        5235,
        9936,
        2403,
        3873,
        412,
        1093,
        2074,
        469,
        38668,
        235,
        813,
        1533,
        668,
        39586,
        2026,
        7593,
        1045,
        60,
        23897,
        2221,
        37520,
        4554,
        186,
        4782,
        6149,
        3312,
        21877,
        10887,
        40893,
        2330,
        59,
        11203,
        1818,
        1629,
        14713,
        33654,
        332,
        4550,
        10372,
        6880,
        1808,
        250,
        3092,
        9811,
        232,
        22465,
        1445,
        249,
        1412,
        134,
        52,
        23901,
        34841,
        6574,
        120,
        17703,
        8074,
        40623,
        3571,
        10187,
        6747,
        35857,
        226,
        10908,
        34403,
        28825,
        2041,
        783,
        3731,
        189,
        143,
        142,
        44044,
        863,
        4211,
        10080,
        225,
        3159,
        223,
        37982,
        40423,
        37467,
        563,
        63,
        39685,
        37141,
        2259,
        270,
        61,
        39686,
        3958,
        11013,
        6075,
        243,
        35928,
        379,
        8525,
        2287,
        1535,
        1425,
        3616,
        19445,
        1426
    ],
    "2395": [
        33095,
        32175,
        35838,
        34547,
        31914,
        33433,
        19775,
        27441,
        33502,
        13125,
        24893,
        25835,
        32282,
        36949,
        35788,
        35503,
        32038,
        9863,
        28171,
        23151,
        39940,
        10014,
        27741,
        440,
        12815,
        37569,
        37952,
        35839,
        2547,
        170,
        79,
        1557,
        23325,
        20057,
        39575,
        21843,
        3369,
        23327,
        1836,
        33834,
        2161,
        31374,
        23209,
        30736,
        2596,
        6802,
        9253,
        6979,
        40902,
        29163,
        2555,
        30484,
        4722,
        2942,
        10378,
        38524,
        3098,
        22101,
        7082,
        25777,
        5262,
        2923,
        16498,
        20555,
        40763,
        40786,
        35760,
        28621,
        7724,
        35540,
        35847,
        3588,
        7662,
        534,
        1816,
        21507,
        29786,
        1517,
        5958,
        2562,
        30375,
        1965,
        23233,
        6098,
        8557,
        879,
        23273,
        32105,
        8726,
        8407,
        8832,
        37662,
        30363,
        10109,
        38843,
        169,
        38923,
        535,
        17080,
        836,
        5233,
        2604,
        339,
        14289,
        16524,
        18119,
        152,
        2216,
        31680,
        38659,
        11371,
        33362,
        5702,
        12367,
        18277,
        789,
        75,
        30549,
        8934,
        198,
        32093,
        4810,
        5226,
        2582,
        13307,
        3809,
        32555,
        11757,
        17211,
        17821,
        4382,
        154,
        3470,
        21881,
        33668,
        24037,
        1559,
        3420,
        8373,
        33417,
        30649,
        478,
        5485,
        5504,
        2451,
        849,
        12191,
        31229,
        4028,
        1172,
        36475,
        30911,
        42263,
        2619,
        835,
        5034,
        2758,
        36000,
        33031,
        2031,
        22273,
        7004,
        36536,
        341,
        36470,
        6634,
        1602,
        22687,
        5220,
        32032,
        16417,
        30187,
        11123,
        2001,
        38331,
        1827,
        12531,
        2104,
        20847,
        32542,
        36474,
        29758,
        1823,
        8829,
        6773,
        5307,
        22319,
        20973,
        4581,
        1548,
        39597,
        1532,
        20223,
        5507,
        21573,
        23201,
        37426,
        2787,
        1103,
        1541,
        100,
        1727,
        5027,
        1104,
        205,
        28283,
        34494,
        355,
        42668,
        8675,
        27899,
        5355,
        19365,
        538,
        15793,
        7588,
        26,
        36817,
        5854,
        34086,
        34102,
        9926,
        25,
        9941,
        13759,
        12445,
        3667,
        22359,
        390,
        959,
        34822,
        36316,
        960,
        2620,
        8057,
        39194,
        11751,
        855,
        38578,
        40540,
        37450,
        2605,
        37430,
        24133,
        6973,
        2476,
        14227,
        854,
        6211,
        35790,
        38759,
        36653,
        32595,
        32843,
        1642,
        4514,
        41353,
        1568,
        876,
        15579,
        3332,
        40403,
        33836,
        5203,
        171,
        7639,
        2618,
        15119,
        34839,
        35251,
        6112,
        28025,
        19981,
        2150,
        31564,
        4224,
        8687,
        30806,
        1005,
        1728,
        13333,
        10162,
        12431,
        6381,
        421,
        23587,
        342,
        2158,
        5277,
        30015,
        620,
        11499,
        36511,
        846,
        36531,
        37521,
        2415,
        4021,
        6974,
        7785,
        42923,
        32673,
        20047,
        10278,
        14515,
        21353,
        10525,
        8139,
        22,
        17909,
        2903,
        4884,
        24,
        13551,
        8964,
        397,
        2766,
        658,
        1618,
        31430,
        41372,
        10232,
        12611,
        4067,
        33352,
        34076,
        34915,
        16742,
        12883,
        988,
        34449,
        22877,
        6114,
        12321,
        4063,
        28497,
        290,
        407,
        6444,
        32881,
        11405,
        41392,
        1608,
        16049,
        1712,
        18941,
        39725,
        2559,
        4515,
        33726,
        33023,
        36458,
        30344,
        1837,
        36513,
        182,
        35994,
        5909,
        1914,
        3455,
        8542,
        31240,
        6213,
        1108,
        22135,
        27629,
        396,
        167,
        30727,
        23847,
        1236,
        19117,
        40783,
        966,
        1279,
        16123,
        18179,
        40028,
        533,
        34612,
        173,
        8449,
        6758,
        10308,
        33037,
        33113,
        4654,
        9893,
        34561,
        32899,
        35968,
        32995,
        174,
        3974,
        42766,
        33377,
        25867,
        400,
        2965,
        5141,
        13663,
        20709,
        23277,
        32836,
        5712,
        13601,
        7768,
        6,
        6899,
        37779,
        9424,
        10774,
        40392,
        11763,
        39966,
        16011,
        166,
        34177,
        21033,
        6203,
        696,
        1960,
        32951,
        25157,
        39918,
        34368,
        18245,
        37799,
        10033,
        14813,
        10073,
        131,
        17315,
        2254,
        2129,
        8311,
        29854,
        6500,
        23283,
        22313,
        1065,
        677,
        1863,
        4068,
        42033,
        30028,
        28979,
        5940,
        7245,
        200,
        41389,
        23281,
        2510,
        41573,
        1226,
        13599,
        22663,
        419,
        1372,
        21561,
        38474,
        9768,
        28677,
        39587,
        28619,
        10798,
        37786,
        338,
        23421,
        21487,
        33889,
        24277,
        34474,
        2406,
        6956,
        36037,
        31174,
        678,
        4896,
        8937,
        35250,
        4663,
        529,
        687,
        40907,
        623,
        15875,
        567,
        35247,
        38480,
        10321,
        35905,
        33341,
        5300,
        18041,
        31559,
        9391,
        34019,
        11341,
        1508,
        25879,
        561,
        41062,
        15731,
        2245,
        30240,
        3009,
        16486,
        1699,
        30749,
        37571,
        38005,
        7058,
        721,
        5832,
        35067,
        3859,
        38853,
        30740,
        1603,
        957,
        3594,
        3613,
        41440,
        42391,
        33094,
        42264,
        2391,
        508,
        6674,
        39547,
        35240,
        28297,
        9885,
        1133,
        9241,
        38707,
        45,
        34903,
        34832,
        5201,
        2361,
        26165,
        202,
        445,
        329,
        3672,
        32615,
        12711,
        11497,
        5984,
        1231,
        32924,
        861,
        28617,
        3457,
        2934,
        35507,
        17777,
        5074,
        1000,
        34126,
        39710,
        34798,
        31098,
        479,
        481,
        1713,
        31716,
        7980,
        1587,
        41529,
        35249,
        14921,
        10495,
        34550,
        26443,
        36654,
        10869,
        17423,
        31181,
        2109,
        3768,
        130,
        10884,
        3091,
        482,
        3044,
        35298,
        21845,
        2747,
        2113,
        10521,
        5671,
        392,
        1942,
        65,
        8041,
        1882,
        5830,
        46118,
        34289,
        24405,
        25519,
        26243,
        1098,
        10810,
        929,
        35789,
        32262,
        5734,
        177,
        39942,
        23393,
        1881,
        30296,
        5223,
        25607,
        37722,
        10015,
        14075,
        1601,
        3772,
        3972,
        19023,
        34572,
        32094,
        27775,
        573,
        3000,
        28927,
        25859,
        2486,
        969,
        210,
        22865,
        41520,
        35073,
        40174,
        2987,
        30385,
        2577,
        2014,
        37221,
        3125,
        27,
        4752,
        36009,
        605,
        38481,
        6056,
        39324,
        12403,
        30279,
        1254,
        1650,
        21639,
        24701,
        15911,
        37675,
        3137,
        37579,
        2557,
        856,
        29803,
        38573,
        2543,
        1744,
        1167,
        1375,
        41226,
        10156,
        8861,
        3806,
        36652,
        32582,
        6586,
        343,
        4214,
        278,
        19875,
        2820,
        6311,
        32729,
        1048,
        156,
        43778,
        12863,
        2993,
        472,
        1293,
        3869,
        1710,
        40327,
        944,
        183,
        64,
        22997,
        165,
        30901,
        40908,
        37578,
        4801,
        31178,
        7845,
        41521,
        9383,
        4584,
        916,
        6609,
        35835,
        33478,
        23067,
        1860,
        5040,
        550,
        4332,
        37984,
        3827,
        2108,
        40911,
        9441,
        31783,
        40679,
        21439,
        3228,
        34262,
        6377,
        1840,
        21,
        33532,
        961,
        21085,
        11307,
        209,
        37993,
        42822,
        4853,
        4723,
        95,
        17249,
        1703,
        7,
        11319,
        2558,
        3363,
        3819,
        28,
        35589,
        1195,
        4684,
        4240,
        3736,
        2608,
        11665,
        23135,
        553,
        38555,
        3008,
        36425,
        3327,
        36027,
        35220,
        46652,
        33540,
        12929,
        907,
        1846,
        37890,
        238,
        33589,
        7720,
        113,
        10572,
        29,
        34176,
        38009,
        4720,
        1555,
        708,
        4618,
        168,
        832,
        33019,
        5992,
        36432,
        32961,
        9884,
        4962,
        18939,
        34566,
        39551,
        1037,
        42203,
        28155,
        39355,
        41074,
        27681,
        11837,
        3822,
        5682,
        16526,
        38611,
        180,
        37975,
        37976,
        34591,
        2337,
        16005,
        16051,
        1562,
        20053,
        473,
        919,
        31592,
        4024,
        941,
        40682,
        24075,
        40842,
        1872,
        14333,
        1218,
        688,
        39469,
        9883,
        3691,
        8215,
        8795,
        471,
        40957,
        817,
        23309,
        2742,
        2816,
        40351,
        38119,
        30386,
        178,
        12281,
        5341,
        41777,
        3712,
        18497,
        14283,
        33983,
        23673,
        15651,
        3024,
        9331,
        19151,
        42765,
        18677,
        1607,
        35843,
        37202,
        21939,
        1693,
        2105,
        2362,
        2567,
        32360,
        8685,
        2404,
        19221,
        34096,
        36023,
        6129,
        2331,
        1985,
        327,
        26453,
        34129,
        41778,
        2683,
        764,
        1459,
        2718,
        4470,
        447,
        37393,
        2200,
        2783,
        13659,
        1651,
        39527,
        2549,
        1538,
        19995,
        744,
        3132,
        10257,
        497,
        4486,
        32962,
        18005,
        1349,
        4415,
        34863,
        11227,
        5530,
        2110,
        2741,
        2283,
        4066,
        42825,
        795,
        417,
        2153,
        39292,
        935,
        19871,
        40935,
        10360,
        39948,
        322,
        351,
        34445,
        10379,
        1127,
        14749,
        19291,
        38529,
        1565,
        40714,
        927,
        30276,
        2369,
        4548,
        2231,
        36167,
        3834,
        34284,
        33966,
        3877,
        38483,
        926,
        691,
        326,
        21539,
        1198,
        37522,
        12753,
        2931,
        527,
        2159,
        763,
        34745,
        41109,
        1210,
        8799,
        14623,
        3036,
        19157,
        6165,
        163,
        347,
        1932,
        2717,
        12767,
        853,
        6902,
        311,
        36427,
        2966,
        3151,
        9916,
        4940,
        6201,
        36838,
        8241,
        10588,
        39119,
        307,
        39811,
        19369,
        10282,
        33419,
        3668,
        24705,
        37714,
        798,
        5250,
        181,
        9981,
        37598,
        6918,
        39130,
        39592,
        2039,
        6583,
        16303,
        2781,
        42941,
        31549,
        39063,
        308,
        3180,
        3433,
        1652,
        3765,
        28537,
        353,
        6919,
        40852,
        3322,
        30251,
        30503,
        1040,
        2521,
        37345,
        7522,
        5440,
        35180,
        457,
        36423,
        6303,
        20533,
        325,
        28201,
        41899,
        10607,
        41514,
        4411,
        1941,
        4477,
        5249,
        19,
        4532,
        40906,
        3969,
        29836,
        34034,
        38537,
        34134,
        11919,
        11179,
        2933,
        32998,
        16159,
        15069,
        928,
        17681,
        8179,
        6900,
        607,
        25099,
        1490,
        2226,
        43684,
        36726,
        1543,
        3182,
        970,
        34914,
        2836,
        40506,
        4062,
        16726,
        25589,
        8786,
        31223,
        878,
        446,
        4444,
        4536,
        2757,
        10611,
        36510,
        4599,
        10165,
        38612,
        1868,
        15489,
        3549,
        943,
        2402,
        8476,
        3023,
        3355,
        2815,
        1491,
        28089,
        3614,
        2744,
        4823,
        32983,
        17893,
        8216,
        8158,
        197,
        5292,
        4154,
        5454,
        23623,
        37096,
        1589,
        175,
        5200,
        3800,
        4081,
        3194,
        32670,
        1212,
        2684,
        6868,
        21483,
        85,
        2916,
        1179,
        10049,
        15417,
        712,
        184,
        31691,
        10319,
        10346,
        1878,
        34599,
        40594,
        35964,
        282,
        15873,
        754,
        8234,
        34866,
        2075,
        21485,
        3907,
        31646,
        7956,
        4086,
        27369,
        36245,
        2246,
        31433,
        8853,
        2112,
        39617,
        12361,
        2546,
        1246,
        7681,
        2686,
        31953,
        20507,
        3451,
        4651,
        32230,
        39936,
        12359,
        3915,
        3251,
        33337,
        1391,
        2826,
        3486,
        162,
        3811,
        2703,
        41380,
        386,
        5267,
        1724,
        28595,
        32580,
        302,
        19825,
        3366,
        5938,
        1128,
        35542,
        328,
        3579,
        685,
        35543,
        36565,
        40090,
        17549,
        41025,
        4468,
        1564,
        1962,
        20115,
        5690,
        23,
        28835,
        38337,
        1706,
        4038,
        40136,
        1792,
        37787,
        34852,
        9346,
        24135,
        890,
        30,
        38098,
        10236,
        4073,
        7960,
        1737,
        3114,
        8769,
        6971,
        38123,
        16696,
        34350,
        31227,
        3021,
        2570,
        4113,
        40356,
        32785,
        12875,
        323,
        39609,
        1842,
        1492,
        35248,
        1537,
        35834,
        20001,
        36632,
        36429,
        610,
        2603,
        19831,
        2912,
        37379,
        2706,
        8123,
        38069,
        9107,
        1068,
        38544,
        28869,
        2705,
        3432,
        21039,
        5395,
        27737,
        31147,
        1771,
        7106,
        27787,
        42897,
        11857,
        2938,
        5505,
        5953,
        10396,
        35079,
        9881,
        33051,
        27655,
        3550,
        1264,
        32828,
        627,
        2579,
        14093,
        37657,
        33003,
        2284,
        3505,
        36144,
        23351,
        204,
        3313,
        350,
        30027,
        1746,
        1450,
        17115,
        3900,
        4013,
        1333,
        4662,
        21019,
        11597,
        37491,
        30060,
        1807,
        11245,
        31150,
        31722,
        20945,
        6055,
        1312,
        1214,
        3425,
        5534,
        31452,
        19815,
        89,
        455,
        12677,
        17092,
        39668,
        39184,
        2228,
        35541,
        1377,
        15689,
        25517,
        3022,
        4879,
        3226,
        41277,
        4719,
        9074,
        800,
        3129,
        2489,
        35427,
        17687,
        2921,
        7419,
        23259,
        34927,
        25939,
        19843,
        20147,
        34754,
        3399,
        7955,
        31764,
        1638,
        1873,
        31904,
        29722,
        3407,
        2929,
        14397,
        3001,
        35062,
        15863,
        38127,
        9426,
        22729,
        16067,
        2709,
        1891,
        3870,
        2363,
        3673,
        37487,
        161,
        16518,
        1936,
        1547,
        35183,
        1672,
        16397,
        35821,
        340,
        4189,
        39133,
        5032,
        9922,
        3812,
        24855,
        3112,
        2151,
        7655,
        1698,
        3936,
        4574,
        7048,
        27831,
        31892,
        591,
        2573,
        22215,
        5420,
        21999,
        8195,
        4061,
        17671,
        32379,
        17705,
        4191,
        3281,
        40504,
        2707,
        1991,
        36516,
        3436,
        2613,
        5636,
        2038,
        17873,
        1711,
        22147,
        38125,
        1972,
        3810,
        1493,
        14513,
        36793,
        3879,
        31631,
        13585,
        12391,
        593,
        7079,
        558,
        2282,
        31965,
        6511,
        34028,
        2257,
        11933,
        38235,
        4935,
        40964,
        34055,
        2828,
        28791,
        33733,
        18155,
        525,
        38538,
        10271,
        30091,
        3388,
        35757,
        1569,
        8676,
        32607,
        11235,
        37374,
        39539,
        7647,
        37509,
        32596,
        7769,
        486,
        20787,
        32947,
        2810,
        2740,
        13535,
        8956,
        3615,
        9061,
        12793,
        38101,
        3655,
        37990,
        30016,
        41619,
        40532,
        37029,
        34106,
        4800,
        19703,
        18115,
        3875,
        6397,
        7307,
        1845,
        2032,
        23311,
        7152,
        35075,
        31741,
        4151,
        31251,
        22999,
        880,
        30485,
        3020,
        67,
        1735,
        37268,
        41345,
        1524,
        33371,
        3761,
        518,
        4614,
        5468,
        57,
        32313,
        12963,
        490,
        3754,
        444,
        5675,
        714,
        26351,
        333,
        5070,
        962,
        33300,
        1243,
        1705,
        24833,
        2835,
        18771,
        31442,
        2687,
        35078,
        2749,
        569,
        10161,
        2926,
        3692,
        3437,
        3660,
        5028,
        5278,
        7661,
        22831,
        13409,
        5311,
        614,
        13163,
        28221,
        9989,
        34580,
        12471,
        30382,
        32455,
        11859,
        17127,
        24011,
        9969,
        682,
        37324,
        37245,
        4773,
        28013,
        1583,
        34577,
        42506,
        19877,
        41491,
        2762,
        36993,
        2825,
        1975,
        1454,
        930,
        1738,
        877,
        15905,
        3297,
        19311,
        41834,
        34607,
        1458,
        4242,
        2699,
        41762,
        33310,
        11759,
        3444,
        12243,
        21407,
        7193,
        9513,
        37798,
        9996,
        9693,
        924,
        18897,
        9756,
        873,
        36800,
        34771,
        34975,
        2225,
        709,
        160,
        613,
        3701,
        11697,
        592,
        31318,
        86,
        6629,
        31931,
        31588,
        3002,
        17389,
        5075,
        3501,
        36902,
        33506,
        22789,
        8,
        19873,
        273,
        17074,
        36015,
        16650,
        3185,
        31804,
        34427,
        33027,
        27811,
        8375,
        105,
        19585,
        1314,
        1502,
        9822,
        39792,
        34787,
        39799,
        38669,
        2223,
        34522,
        28249,
        385,
        477,
        32948,
        21437,
        918,
        7592,
        6917,
        1695,
        1470,
        2544,
        1189,
        23755,
        812,
        3131,
        24415,
        7334,
        1546,
        35313,
        2688,
        11835,
        2152,
        2333,
        39583,
        40961,
        34643,
        16530,
        612,
        34905,
        20971,
        13261,
        31890,
        38199,
        6774,
        1371,
        2128,
        32772,
        10359,
        33850,
        24909,
        28833,
        31422,
        7779,
        37956,
        9510,
        19947,
        31790,
        32979,
        306,
        40513,
        36266,
        31404,
        30383,
        37979,
        10447,
        40358,
        37154,
        22099,
        27525,
        1175,
        10800,
        32483,
        5375,
        584,
        11829,
        38753,
        33583,
        37926,
        2214,
        20027,
        3418,
        27393,
        9776,
        31173,
        37510,
        35076,
        2501,
        8501,
        3196,
        32792,
        33434,
        6672,
        18411,
        3424,
        32171,
        31821,
        4244,
        5658,
        20,
        3199,
        1708,
        37870,
        17521,
        40529,
        31884,
        298,
        2571,
        283,
        3136,
        4209,
        32608,
        3101,
        858,
        16027,
        886,
        37283,
        838,
        6727,
        37458,
        740,
        7981,
        30895,
        39699,
        33314,
        18097,
        3619,
        39277,
        6324,
        16201,
        5688,
        6374,
        2565,
        38126,
        2553,
        20785,
        1356,
        12763,
        2213,
        33788,
        1986,
        19997,
        8763,
        6633,
        31580,
        38268,
        5474,
        11433,
        39137,
        2738,
        545,
        22535,
        31893,
        19363,
        32526,
        18767,
        21835,
        3881,
        38122,
        23013,
        1915,
        30205,
        40148,
        3325,
        68,
        2624,
        38534,
        3937,
        30123,
        2142,
        30795,
        1519,
        6375,
        271,
        37447,
        3836,
        33299,
        1453,
        5477,
        37484,
        39136,
        239,
        38129,
        24625,
        3975,
        3162,
        32182,
        40074,
        12039,
        30654,
        3823,
        6030,
        2127,
        6970,
        5935,
        23409,
        10030,
        33489,
        1865,
        39506,
        1156,
        26441,
        37232,
        2004,
        37254,
        38150,
        4114,
        39138,
        19325,
        31246,
        28977,
        38020,
        15,
        1675,
        1069,
        2576,
        19501,
        470,
        35656,
        2986,
        34901,
        13201,
        2822,
        5131,
        17919,
        21405,
        21013,
        1498,
        2382,
        21185,
        1193,
        22547,
        1574,
        3947,
        58,
        2409,
        53,
        31798,
        20083,
        1550,
        10507,
        37206,
        31157,
        6901,
        25013,
        33047,
        40128,
        3035,
        37611,
        9438,
        38256,
        9314,
        107,
        35557,
        40956,
        40497,
        31610,
        38671,
        31771,
        18845,
        1083,
        5129,
        12031,
        6512,
        8194,
        38924,
        5041,
        6277,
        37989,
        37972,
        11021,
        7109,
        7674,
        17505,
        12291,
        2885,
        8217,
        2735,
        1200,
        32438,
        41433,
        38128,
        30307,
        2771,
        48,
        28387,
        4208,
        5082,
        4933,
        272,
        37395,
        38830,
        8764,
        12365,
        38804,
        32568,
        3438,
        19769,
        3878,
        9522,
        6981,
        5908,
        38118,
        31427,
        22043,
        925,
        2829,
        8235,
        33253,
        352,
        33792,
        37302,
        35642,
        38535,
        6920,
        19429,
        39129,
        38301,
        2803,
        1139,
        5968,
        21995,
        5941,
        532,
        2036,
        40750,
        33197,
        12149,
        5258,
        5104,
        331,
        11285,
        38091,
        16211,
        16393,
        6520,
        1655,
        1892,
        31573,
        279,
        2805,
        8538,
        3099,
        2548,
        18229,
        3935,
        2598,
        36028,
        37151,
        16918,
        9919,
        29843,
        30039,
        50,
        15315,
        266,
        1581,
        40483,
        25063,
        21167,
        3110,
        6448,
        2084,
        727,
        20081,
        34565,
        4087,
        1163,
        1136,
        6682,
        280,
        1251,
        951,
        37007,
        31376,
        506,
        3837,
        2484,
        2813,
        269,
        36882,
        21821,
        3876,
        39701,
        2572,
        5088,
        14199,
        32407,
        751,
        10815,
        34662,
        1137,
        7627,
        28423,
        4657,
        31080,
        34451,
        4119,
        4616,
        39244,
        4483,
        31692,
        23607,
        17917,
        19989,
        1704,
        4264,
        27663,
        17141,
        40230,
        11841,
        27723,
        28391,
        38379,
        394,
        17497,
        2769,
        2970,
        4808,
        9587,
        11633,
        889,
        4690,
        2719,
        9806,
        29687,
        136,
        36563,
        38084,
        22199,
        31405,
        4051,
        11197,
        7751,
        14511,
        25429,
        2044,
        11111,
        6067,
        263,
        37716,
        36552,
        4929,
        8917,
        32981,
        41558,
        285,
        20431,
        2035,
        22817,
        6452,
        3750,
        35365,
        27833,
        8624,
        27965,
        39463,
        495,
        33012,
        3104,
        38254,
        10721,
        633,
        34836,
        3225,
        28817,
        39808,
        34966,
        1668,
        92,
        310,
        2694,
        388,
        33531,
        3054,
        1690,
        4549,
        12467,
        40530,
        39535,
        38940,
        3391,
        3305,
        965,
        38860,
        2736,
        34741,
        5494,
        34410,
        34973,
        6547,
        7904,
        2106,
        56,
        5525,
        12967,
        38276,
        967,
        34012,
        1775,
        1667,
        2818,
        3630,
        29095,
        39139,
        5234,
        33041,
        4080,
        2985,
        196,
        2913,
        2227,
        3845,
        5231,
        3723,
        37475,
        1485,
        3146,
        9978,
        22189,
        1974,
        28669,
        37259,
        33487,
        1022,
        103,
        18153,
        35972,
        31706,
        1327,
        3656,
        22225,
        23945,
        3059,
        9934,
        956,
        29787,
        2204,
        21603,
        4416,
        21511,
        5091,
        3213,
        1292,
        2772,
        2203,
        1591,
        852,
        7081,
        41635,
        36593,
        4903,
        8753,
        15915,
        1239,
        1157,
        973,
        36704,
        3927,
        31859,
        5039,
        41694,
        40454,
        19319,
        9952,
        11739,
        36548,
        39523,
        2552,
        19993,
        31630,
        18893,
        9736,
        7625,
        782,
        16157,
        10444,
        77,
        37965,
        32023,
        40677,
        12119,
        3176,
        33018,
        369,
        3166,
        6428,
        9479,
        22693,
        18137,
        39131,
        32949,
        18195,
        3075,
        5112,
        25397,
        1050,
        5628,
        38851,
        7405,
        5155,
        11061,
        971,
        19647,
        831,
        3880,
        40708,
        22145,
        1110,
        5023,
        33089,
        6636,
        2367,
        23037,
        5473,
        148,
        589,
        2554,
        21177,
        35756,
        21491,
        38003,
        22507,
        27991,
        5597,
        35303,
        3372,
        127,
        31049,
        2255,
        31737,
        7793,
        23079,
        3193,
        69,
        11017,
        345,
        4101,
        40059,
        1483,
        13029,
        1663,
        3631,
        38619,
        34636,
        34669,
        616,
        37403,
        7103,
        7575,
        21729,
        1769,
        94,
        8410,
        287,
        37998,
        6093,
        11771,
        33490,
        1660,
        1599,
        24873,
        1885,
        18937,
        43299,
        38408,
        7551,
        28701,
        36884,
        2786,
        2581,
        132,
        1893,
        2827,
        8415,
        1249,
        34525,
        630,
        98,
        2076,
        19855,
        37481,
        551,
        11741,
        8130,
        5763,
        604,
        5276,
        13655,
        706,
        9882,
        1570,
        9540,
        349,
        40196,
        37338,
        38136,
        41776,
        1694,
        284,
        37171,
        18635,
        24629,
        37451,
        5997,
        1688,
        14237,
        14913,
        4807,
        1988,
        1469,
        55,
        37435,
        8140,
        38993,
        39196,
        23251,
        36124,
        344,
        29325,
        35828,
        38572,
        6712,
        37958,
        38920,
        37490,
        20509,
        22893,
        17729,
        153,
        1516,
        33206,
        1745,
        1661,
        37036,
        126,
        261,
        33184,
        15085,
        2545,
        19111,
        27727,
        33743,
        2834,
        530,
        6625,
        2467,
        36456,
        17102,
        229,
        10136,
        33899,
        6008,
        21677,
        38889,
        1086,
        1534,
        35334,
        17651,
        32660,
        19985,
        3295,
        12651,
        16894,
        8516,
        2907,
        2882,
        35997,
        32696,
        18495,
        998,
        37349,
        31537,
        25649,
        38062,
        24455,
        5725,
        36522,
        38186,
        31043,
        37140,
        23199,
        11268,
        11421,
        39590,
        35639,
        7619,
        32245,
        39135,
        35860,
        32648,
        2230,
        37752,
        195,
        3359,
        3561,
        22651,
        9028,
        17,
        1473,
        729,
        25183,
        23321,
        6166,
        40571,
        1897,
        38124,
        35203,
        32301,
        27943,
        24439,
        9181,
        4132,
        4615,
        31733,
        2308,
        34825,
        40166,
        159,
        2704,
        3335,
        18465,
        4060,
        31988,
        40004,
        577,
        32494,
        5273,
        2089,
        17265,
        34542,
        30544,
        33,
        6676,
        76,
        14827,
        33840,
        2243,
        3576,
        115,
        6980,
        12979,
        5197,
        8436,
        34104,
        1164,
        28999,
        37806,
        35241,
        39039,
        34934,
        10336,
        5337,
        33486,
        6702,
        38080,
        3358,
        267,
        15611,
        1858,
        1456,
        1722,
        476,
        14967,
        1554,
        1664,
        483,
        37869,
        1219,
        6116,
        3079,
        1592,
        288,
        16035,
        10330,
        230,
        36976,
        32601,
        3294,
        8285,
        31636,
        8240,
        1123,
        6023,
        1224,
        40748,
        9834,
        34051,
        4504,
        670,
        29527,
        3627,
        801,
        2364,
        521,
        4744,
        25283,
        2253,
        942,
        30230,
        5618,
        10889,
        33203,
        20541,
        1853,
        4121,
        10620,
        13167,
        4427,
        1617,
        1628,
        19685,
        38000,
        38378,
        32887,
        40610,
        31964,
        909,
        2252,
        31670,
        15883,
        10087,
        387,
        4339,
        1145,
        3435,
        859,
        2244,
        39221,
        41006,
        3012,
        34984,
        3130,
        857,
        25731,
        37823,
        32867,
        2156,
        80,
        28623,
        5967,
        671,
        40137,
        16732,
        5891,
        5600,
        37347,
        2609,
        17619,
        4199,
        4597,
        17624,
        8011,
        15059,
        1579,
        7177,
        653,
        5829,
        9812,
        37555,
        2229,
        31933,
        99,
        1509,
        915,
        37497,
        36906,
        4789,
        38131,
        17291,
        20199,
        3285,
        3840,
        10460,
        10490,
        39195,
        18095,
        11385,
        2817,
        22297,
        31637,
        1778,
        37991,
        34712,
        31339,
        38161,
        14131,
        568,
        38731,
        37023,
        40167,
        19257,
        8424,
        5342,
        3710,
        411,
        3006,
        24121,
        4981,
        28907,
        2789,
        3932,
        97,
        18671,
        364,
        35983,
        8129,
        13185,
        42468,
        21105,
        1669,
        6701,
        39199,
        2508,
        109,
        1180,
        31952,
        39790,
        38959,
        1590,
        21549,
        38120,
        2164,
        5945,
        4975,
        5684,
        6087,
        33573,
        289,
        36587,
        8394,
        1087,
        39026,
        144,
        34800,
        1530,
        621,
        40046,
        32878,
        22433,
        21273,
        14941,
        4443,
        37525,
        39730,
        33671,
        38138,
        37300,
        31698,
        1025,
        3653,
        73,
        1852,
        15051,
        29785,
        21681,
        9433,
        33985,
        19965,
        9810,
        32083,
        8426,
        39017,
        13349,
        129,
        2799,
        10965,
        29589,
        636,
        3545,
        42657,
        21809,
        9200,
        3271,
        2809,
        11703,
        1886,
        1740,
        914,
        30652,
        8553,
        14833,
        10578,
        6509,
        20031,
        40397,
        11533,
        150,
        30048,
        3807,
        27631,
        2495,
        32935,
        2024,
        260,
        3467,
        2034,
        39582,
        10719,
        32901,
        15479,
        158,
        141,
        6707,
        30694,
        240,
        406,
        34510,
        1097,
        5162,
        13161,
        40010,
        11241,
        36934,
        32370,
        39417,
        10110,
        10370,
        35434,
        9533,
        14741,
        1472,
        5081,
        38656,
        6164,
        6117,
        4197,
        3638,
        37496,
        1142,
        4050,
        5478,
        4183,
        1912,
        2963,
        34964,
        40815,
        3272,
        2224,
        2542,
        62,
        6347,
        18001,
        5670,
        12185,
        37739,
        34249,
        16009,
        330,
        31845,
        5834,
        996,
        5071,
        20127,
        21327,
        277,
        487,
        32937,
        35712,
        1623,
        27989,
        790,
        28891,
        40145,
        20899,
        18679,
        36296,
        9856,
        40595,
        22509,
        7160,
        12679,
        16,
        41911,
        237,
        10213,
        1186,
        27721,
        5760,
        12487,
        33475,
        1929,
        384,
        17086,
        37964,
        2892,
        9948,
        30831,
        395,
        606,
        2503,
        32212,
        38790,
        4039,
        37962,
        40591,
        246,
        8536,
        20583,
        17827,
        32866,
        1325,
        32686,
        37584,
        952,
        5287,
        37105,
        6875,
        36740,
        26055,
        241,
        4054,
        27947,
        24765,
        5140,
        125,
        953,
        4999,
        101,
        10808,
        36094,
        9712,
        2924,
        19067,
        2162,
        31478,
        21431,
        40880,
        28883,
        9175,
        31044,
        3713,
        1486,
        31629,
        34338,
        245,
        2416,
        29529,
        16890,
        17741,
        14829,
        39468,
        14811,
        3874,
        36873,
        2215,
        38390,
        6989,
        587,
        3389,
        22265,
        467,
        22777,
        38883,
        40839,
        9520,
        14653,
        93,
        5089,
        7580,
        4503,
        2165,
        37601,
        33421,
        32214,
        253,
        1194,
        5030,
        34279,
        35605,
        34280,
        2251,
        31338,
        33797,
        5079,
        845,
        2748,
        14765,
        10357,
        20237,
        37968,
        34209,
        39567,
        3464,
        16982,
        39030,
        4286,
        36978,
        19367,
        10397,
        336,
        3081,
        2602,
        40272,
        9821,
        37599,
        1013,
        32189,
        37587,
        9656,
        34290,
        135,
        2819,
        1374,
        652,
        5678,
        1864,
        40359,
        693,
        10456,
        9367,
        992,
        297,
        1132,
        31456,
        1604,
        38157,
        37744,
        7867,
        34834,
        40803,
        375,
        90,
        1316,
        2043,
        247,
        14527,
        13331,
        242,
        2814,
        116,
        38297,
        5184,
        850,
        102,
        41783,
        31163,
        4898,
        36649,
        36220,
        1571,
        35643,
        35222,
        3577,
        14989,
        39634,
        5052,
        1067,
        295,
        2130,
        9613,
        40550,
        37178,
        3230,
        2285,
        7645,
        39198,
        185,
        145,
        2037,
        603,
        1844,
        6045,
        236,
        13203,
        10210,
        301,
        912,
        10137,
        516,
        1222,
        1161,
        4334,
        6033,
        2804,
        776,
        1567,
        13145,
        40165,
        122,
        1281,
        37561,
        36407,
        2040,
        3299,
        10793,
        1721,
        5476,
        6012,
        12413,
        1070,
        23121,
        4726,
        33739,
        31500,
        41312,
        335,
        20457,
        840,
        110,
        123,
        20239,
        27829,
        36633,
        38145,
        3568,
        3858,
        833,
        10163,
        74,
        3349,
        12189,
        555,
        38284,
        37999,
        39533,
        40417,
        1471,
        874,
        1465,
        40056,
        39388,
        33948,
        2574,
        38909,
        505,
        21855,
        2405,
        15379,
        1337,
        3825,
        14719,
        1806,
        4667,
        2564,
        738,
        35252,
        31417,
        618,
        511,
        2390,
        11761,
        5114,
        1691,
        2523,
        667,
        19961,
        66,
        1606,
        33026,
        1221,
        17247,
        370,
        1674,
        7590,
        1466,
        9539,
        586,
        39071,
        31710,
        40045,
        40974,
        15061,
        3604,
        11843,
        20183,
        40496,
        334,
        11525,
        37210,
        33354,
        1594,
        18055,
        17106,
        39040,
        1678,
        40776,
        360,
        13115,
        286,
        318,
        72,
        40249,
        20075,
        3298,
        5962,
        10709,
        1397,
        23133,
        9041,
        5973,
        1542,
        37614,
        1707,
        1046,
        36828,
        35254,
        39622,
        34618,
        33988,
        3345,
        5835,
        16355,
        3572,
        31700,
        37576,
        1685,
        34933,
        9284,
        2930,
        21743,
        4725,
        292,
        18689,
        251,
        35376,
        38691,
        30030,
        38083,
        38302,
        2280,
        324,
        25681,
        18295,
        18507,
        121,
        509,
        649,
        3835,
        3846,
        32136,
        10465,
        635,
        18247,
        296,
        2575,
        35849,
        14467,
        2002,
        519,
        15613,
        2487,
        35138,
        4511,
        24231,
        3909,
        38680,
        24703,
        38670,
        8879,
        321,
        11887,
        488,
        5153,
        35889,
        157,
        16353,
        5886,
        39783,
        2701,
        19839,
        34497,
        25139,
        34382,
        41120,
        10194,
        1230,
        1848,
        71,
        40092,
        1684,
        11785,
        690,
        32802,
        1019,
        3808,
        234,
        10138,
        2927,
        14345,
        6811,
        626,
        23333,
        968,
        1614,
        15565,
        646,
        40716,
        37517,
        1572,
        4439,
        96,
        1,
        3010,
        309,
        33731,
        4196,
        38093,
        34543,
        3053,
        7479,
        12809,
        10790,
        1588,
        20689,
        456,
        15699,
        35641,
        2335,
        860,
        39326,
        2116,
        10224,
        2964,
        9493,
        8915,
        913,
        799,
        1536,
        34281,
        5274,
        3503,
        5833,
        18007,
        2400,
        40221,
        888,
        233,
        276,
        34664,
        1261,
        31701,
        147,
        1021,
        2157,
        24031,
        1676,
        6645,
        15109,
        1082,
        19505,
        16706,
        1810,
        14645,
        1673,
        8521,
        4186,
        248,
        1088,
        33046,
        1887,
        39979,
        7525,
        28223,
        36525,
        37750,
        19163,
        12549,
        7148,
        4586,
        37597,
        39572,
        23269,
        17969,
        1578,
        12835,
        28121,
        21563,
        9938,
        34667,
        2795,
        2389,
        3769,
        31109,
        21553,
        4023,
        36029,
        35413,
        149,
        16512,
        12175,
        2800,
        8086,
        40085,
        10242,
        30156,
        2595,
        274,
        1250,
        2980,
        2167,
        104,
        2222,
        1573,
        4044,
        31018,
        34620,
        1410,
        291,
        3231,
        1313,
        294,
        501,
        655,
        576,
        4192,
        39570,
        39534,
        694,
        23107,
        3514,
        7054,
        4049,
        17669,
        4814,
        37086,
        590,
        16668,
        2316,
        106,
        424,
        10568,
        41930,
        257,
        3315,
        1563,
        634,
        9455,
        9905,
        3270,
        33028,
        18,
        435,
        489,
        37117,
        23289,
        19901,
        3116,
        7817,
        1482,
        5150,
        6573,
        3844,
        4181,
        12293,
        218,
        33383,
        2012,
        4052,
        2566,
        1149,
        934,
        771,
        1956,
        5235,
        910,
        2561,
        9936,
        5630,
        2403,
        9289,
        3873,
        412,
        1093,
        2074,
        469,
        8184,
        2025,
        38668,
        235,
        1826,
        813,
        1533,
        668,
        3838,
        8899,
        23973,
        8595,
        42740,
        34077,
        39586,
        19467,
        2026,
        7593,
        37446,
        1045,
        8841,
        3361,
        60,
        3776,
        1184,
        2221,
        40879,
        1899,
        2700,
        37520,
        940,
        1946,
        4554,
        186,
        16592,
        38328,
        15451,
        228,
        1138,
        12461,
        510,
        5143,
        252,
        22065,
        1017,
        4782,
        1884,
        36754,
        20231,
        2904,
        6149,
        3312,
        36022,
        11079,
        21877,
        39681,
        10887,
        20853,
        1889,
        2330,
        19681,
        59,
        1575,
        7062,
        4928,
        865,
        32271,
        4551,
        9379,
        15583,
        1818,
        29976,
        4563,
        11239,
        3229,
        1629,
        7088,
        30034,
        40934,
        14713,
        35988,
        33654,
        36666,
        2155,
        2030,
        332,
        17667,
        11617,
        36309,
        4550,
        10372,
        6880,
        16385,
        222,
        15809,
        1808,
        250,
        3092,
        4083,
        10237,
        6746,
        9811,
        17088,
        5680,
        958,
        232,
        244,
        32717,
        4025,
        9562,
        9750,
        7791,
        1445,
        35364,
        8630,
        25159,
        249,
        39078,
        1412,
        134,
        5344,
        52,
        1442,
        6574,
        120,
        5356,
        40075,
        598,
        32590,
        3654,
        9330,
        17703,
        20125,
        8074,
        40623,
        3571,
        10217,
        11783,
        6261,
        32630,
        8183,
        17831,
        5475,
        1018,
        6747,
        40983,
        3609,
        12139,
        15605,
        6771,
        6205,
        35857,
        8897,
        15377,
        2087,
        206,
        10623,
        39012,
        1561,
        226,
        4375,
        34403,
        28825,
        8777,
        5594,
        10135,
        2041,
        8812,
        783,
        41283,
        39990,
        15913,
        3637,
        3731,
        552,
        36483,
        189,
        143,
        990,
        8425,
        13367,
        133,
        142,
        10079,
        1600,
        863,
        4211,
        10080,
        225,
        7395,
        6895,
        37204,
        3159,
        23015,
        223,
        8206,
        1448,
        10562,
        5022,
        356,
        17090,
        10155,
        37982,
        4198,
        15225,
        31196,
        554,
        9065,
        41426,
        3202,
        146,
        6889,
        275,
        3670,
        563,
        63,
        17895,
        40266,
        39685,
        2288,
        4262,
        37141,
        2259,
        2494,
        270,
        193,
        20079,
        16419,
        61,
        39686,
        27519,
        12897,
        2281,
        111,
        3460,
        6730,
        3958,
        3839,
        11013,
        243,
        35928,
        379,
        8525,
        24465,
        27815,
        2287,
        16131,
        1535,
        3689,
        427,
        1666,
        5914,
        13769,
        33753,
        8277,
        17513,
        1726,
        30519,
        2708,
        2383,
        12887,
        3676,
        18191,
        1425,
        37769,
        15865,
        3616,
        15957,
        25717,
        33670,
        4088,
        11275,
        3317,
        1426,
        37476,
        3290,
        17599
    ]
}